README.md
ps2.py
setup.py
ps2.egg-info/PKG-INFO
ps2.egg-info/SOURCES.txt
ps2.egg-info/dependency_links.txt
ps2.egg-info/entry_points.txt
ps2.egg-info/requires.txt
ps2.egg-info/top_level.txt